[
  {
    "titulo": "Como ganar amigos e influir en las personas",
    "autor": "Dale Carnegie",
    "idioma": "Español",
    "categoria": "Crecimiento personal",
    "imagen": "https://images.cdn3.buscalibre.com/fit-in/360x360/e8/24/e824f4d5c2ac00478a659ce59f31b0f2.jpg"
  },
  {
    "titulo": "El hombre más rico de babilonia",
    "autor": "George S. Clason",
    "idioma": "Español",
    "categoria": "Crecimiento personal",
    "imagen": "https://images.cdn3.buscalibre.com/fit-in/360x360/f7/02/f70261428450baeb598dde9e0bce7fc8.jpg"
  },
  {
    "titulo": "Misery",
    "autor": "STEPHEN KING",
    "idioma": "Español",
    "categoria": "Ciencia ficción",
    "imagen": "https://images.cdn2.buscalibre.com/fit-in/360x360/75/2d/752dea57eb4293211b766526d87a064e.jpg"
  },
  {
    "titulo": "Apocalipsis",
    "autor": "STEPHEN KING",
    "idioma": "Español",
    "categoria": "Ciencia ficción",
    "imagen": "https://images.cdn1.buscalibre.com/fit-in/360x360/61/45/614548e593780a204fe4c31c045a284c.jpg"
  }
]